qt_android_remote/__init__.py
qt_android_remote/android_tv_connection.py
qt_android_remote/logo.png
qt_android_remote/main.py
qt_android_remote/remote_manager.py
qt_android_remote/remote_window.py
qt_android_remote/remote_wizard.py
qt_android_remote-1.0.2.dist-info/licenses/LICENSE
qt_android_remote-1.0.2.dist-info/METADATA
qt_android_remote-1.0.2.dist-info/WHEEL
qt_android_remote-1.0.2.dist-info/entry_points.txt
qt_android_remote-1.0.2.dist-info/top_level.txt
qt_android_remote-1.0.2.dist-info/RECORD
